setup.py
bin/new_relic
newrelic_ops/__init__.py
newrelic_ops/saltstack.py
newrelic_ops.egg-info/PKG-INFO
newrelic_ops.egg-info/SOURCES.txt
newrelic_ops.egg-info/dependency_links.txt
newrelic_ops.egg-info/not-zip-safe
newrelic_ops.egg-info/requires.txt
newrelic_ops.egg-info/top_level.txt