Metadata-Version: 1.0
Name: newrelic-ops
Version: 0.3.dev0
Summary: newrelic manipulation tool
Home-page: https://github.com/Abukamel/newrelic_ops
Author: Ahmed Kamel
Author-email: k.tricky@gmail.com
License: MIT
Keywords: newrelic install saltstack automatic
Platform: UNKNOWN
